MANIFEST.in
README.md
requirements.txt
setup.py
satori_core.egg-info/PKG-INFO
satori_core.egg-info/SOURCES.txt
satori_core.egg-info/dependency_links.txt
satori_core.egg-info/entry_points.txt
satori_core.egg-info/requires.txt
satori_core.egg-info/top_level.txt
satoricore/__init__.py
satoricore/common.py
satoricore/image.py
satoricore/logger.py
satoricore/crawler/__init__.py
satoricore/crawler/basecrawler.py
satoricore/crawler/unixcrawler.py
satoricore/extensions/__init__.py
satoricore/extensions/stat_ext.py
satoricore/extensions/sysinfo.py
satoricore/extensions/timestamp.py
satoricore/file/__init__.py
satoricore/file/__main__.py
satoricore/file/json.py
satoricore/file/pickle.py