Metadata-Version: 1.0
Name: satori-core
Version: 0.1.0
Summary: The building blocks of the Satori-Suite
Home-page: https://github.com/satori-ng/
Author: Satori-NG org
Author-email: satori_ng@email.com
License: UNKNOWN
Platform: UNKNOWN
